Workbook

Sheet Dashboard
A1: Dashboard — Entrada Digital (Google Ads)
A2: Indicadores do período selecionado
A4: Período - Data Início | B4: 46266
A5: Período - Data Fim | B5: 46295
A6: Meta de SLA (minutos) | B6: 30
A9: Total de Leads no Período | D9: Leads Dentro do SLA | G9: % Cumprimento de SLA
A10: =COUNTIFS('Entrada de Leads'!$A$2:$A$400,">="&$B$4,'Entrada de Leads'!$A$2:$A$400,"<="&$B$5) | D10: =COUNTIFS('Entrada de Leads'!$A$2:$A$400,">="&$B$4,'Entrada de Leads'!$A$2:$A$400,"<="&$B$5,'Entrada de Leads'!$I$2:$I$400,"Sim") | G10: =IF(COUNTIFS('Entrada de Leads'!$A$2:$A$400,">="&$B$4,'Entrada de Leads'!$A$2:$A$400,"<="&$B$5)=0,0,COUNTIFS('Entrada de Leads'!$A$2:$A$400,">="&$B$4,'Entrada de Leads'!$A$2:$A$400,"<="&$B$5,'Entrada de Leads'!$I$2:$I$400,"Sim")/(COUNTIFS('Entrada de Leads'!$A$2:$A$400,">="&$B$4,'Entrada de Leads'!$A$2:$A$400,"<="&$B$5)))
A12: Leads Convertidos | D12: Taxa de Conversão | G12: Investimento Total (R$)
A13: =COUNTIFS('Entrada de Leads'!$A$2:$A$400,">="&$B$4,'Entrada de Leads'!$A$2:$A$400,"<="&$B$5,'Entrada de Leads'!$J$2:$J$400,"Convertido") | D13: =IF(COUNTIFS('Entrada de Leads'!$A$2:$A$400,">="&$B$4,'Entrada de Leads'!$A$2:$A$400,"<="&$B$5)=0,0,COUNTIFS('Entrada de Leads'!$A$2:$A$400,">="&$B$4,'Entrada de Leads'!$A$2:$A$400,"<="&$B$5,'Entrada de Leads'!$J$2:$J$400,"Convertido")/(COUNTIFS('Entrada de Leads'!$A$2:$A$400,">="&$B$4,'Entrada de Leads'!$A$2:$A$400,"<="&$B$5))) | G13: =SUM('Campanhas Google Ads'!$E$2:$E$60)
A15: Custo por Lead Médio (R$)
A16: =IF(SUM('Campanhas Google Ads'!$J$2:$J$60)=0,0,SUM('Campanhas Google Ads'!$E$2:$E$60)/SUM('Campanhas Google Ads'!$J$2:$J$60))
A18: Funil de Status (período selecionado)
A19: Status | B19: Quantidade
A20: Novo | B20: =COUNTIFS('Entrada de Leads'!$A$2:$A$400,">="&$B$4,'Entrada de Leads'!$A$2:$A$400,"<="&$B$5,'Entrada de Leads'!$J$2:$J$400,"Novo")
A21: Em contato | B21: =COUNTIFS('Entrada de Leads'!$A$2:$A$400,">="&$B$4,'Entrada de Leads'!$A$2:$A$400,"<="&$B$5,'Entrada de Leads'!$J$2:$J$400,"Em contato")
A22: Qualificado | B22: =COUNTIFS('Entrada de Leads'!$A$2:$A$400,">="&$B$4,'Entrada de Leads'!$A$2:$A$400,"<="&$B$5,'Entrada de Leads'!$J$2:$J$400,"Qualificado")
A23: Proposta enviada | B23: =COUNTIFS('Entrada de Leads'!$A$2:$A$400,">="&$B$4,'Entrada de Leads'!$A$2:$A$400,"<="&$B$5,'Entrada de Leads'!$J$2:$J$400,"Proposta enviada")
A24: Convertido | B24: =COUNTIFS('Entrada de Leads'!$A$2:$A$400,">="&$B$4,'Entrada de Leads'!$A$2:$A$400,"<="&$B$5,'Entrada de Leads'!$J$2:$J$400,"Convertido")
A25: Perdido | B25: =COUNTIFS('Entrada de Leads'!$A$2:$A$400,">="&$B$4,'Entrada de Leads'!$A$2:$A$400,"<="&$B$5,'Entrada de Leads'!$J$2:$J$400,"Perdido")

Sheet Rotina Diária
A1: Data | B1: Conferir novos leads no Google Ads / CRM | C1: Responder leads novos dentro do SLA | D1: Atualizar status de cada lead no funil | E1: Registrar investimento diário das campanhas | F1: Revisar campanhas com CPA/CPL acima da meta | G1: Enviar relatório diário para a equipe | H1: Responsável | I1: Observações
A2: 46266 | B2: Feito | C2: Feito | D2: Feito | E2: Feito | F2: Pendente | G2: Feito | H2: Fernanda
A3: 46267 | B3: Feito | C3: Feito | D3: Feito | E3: Feito | F3: Feito | G3: Feito | H3: Equipe Comercial
A4: 46268 | B4: Feito | C4: Pendente | D4: Feito | E4: Feito | F4: N/A | G4: Pendente | H4: Fernanda
A5: 46269 | B5: Feito | C5: Feito | D5: Feito | E5: Pendente | F5: Feito | G5: Feito | H5: Fernanda
A6: 46270 | B6: Feito | C6: Feito | D6: Pendente | E6: Feito | F6: Feito | G6: Feito | H6: Equipe Comercial

Sheet Entrada de Leads
A1: Data | B1: Hora do Lead | C1: Campanha | D1: Nome do Lead | E1: Telefone/WhatsApp | F1: Tipo de Campanha | G1: Hora do 1º Contato | H1: Tempo de Resposta (min) | I1: SLA Cumprido | J1: Status | K1: Responsável | L1: Valor Estimado da Obra (R$) | M1: Observações
A2: 2026-09-01 | B2: 08:15 | C2: Reforma Residencial - Pesquisa | D2: João Almeida | E2: (11) 99888-1122 | F2: Pesquisa | G2: 08:32 | H2: =IF(OR(B2="",G2=""),"",ROUND((G2-B2)*1440,0)) | I2: =IF(H2="","",IF(H2<=Dashboard!$B$6,"Sim","Não")) | J2: Qualificado | K2: Fernanda | L2: 45000 | M2: Interessado em reforma de cozinha
A3: 2026-09-01 | B3: 09:40 | C3: Construção do Zero - PMax | D3: Marcia Souza | E3: (11) 97777-3344 | F3: Performance Max | G3: 10:10 | H3: =IF(OR(B3="",G3=""),"",ROUND((G3-B3)*1440,0)) | I3: =IF(H3="","",IF(H3<=Dashboard!$B$6,"Sim","Não")) | J3: Em contato | K3: Fernanda | L3: 320000 | M3: Aguardando terreno documentado
A4: 2026-09-01 | B4: 13:05 | C4: Reforma Residencial - Pesquisa | D4: Carlos Nunes | E4: (11) 96666-5566 | F4: Pesquisa | G4: 13:20 | H4: =IF(OR(B4="",G4=""),"",ROUND((G4-B4)*1440,0)) | I4: =IF(H4="","",IF(H4<=Dashboard!$B$6,"Sim","Não")) | J4: Proposta enviada | K4: Equipe Comercial | L4: 60000
A5: 2026-09-02 | B5: 10:00 | C5: Reforma Comercial - Display | D5: Loja Center Sul | E5: (11) 95555-7788 | F5: Display | G5: 10:55 | H5: =IF(OR(B5="",G5=""),"",ROUND((G5-B5)*1440,0)) | I5: =IF(H5="","",IF(H5<=Dashboard!$B$6,"Sim","Não")) | J5: Novo | K5: Fernanda | L5: 80000 | M5: Ligar novamente amanhã
A6: 2026-09-02 | B6: 15:20 | C6: Construção do Zero - PMax | D6: Patrícia Lima | E6: (11) 94444-9900 | F6: Performance Max | G6: 15:35 | H6: =IF(OR(B6="",G6=""),"",ROUND((G6-B6)*1440,0)) | I6: =IF(H6="","",IF(H6<=Dashboard!$B$6,"Sim","Não")) | J6: Convertido | K6: Equipe Comercial | L6: 410000 | M6: Contrato assinado
A7: 2026-09-03 | B7: 11:10 | C7: Reforma Residencial - Pesquisa | D7: Renato Dias | E7: (11) 93333-1212 | F7: Pesquisa | G7: 12:05 | H7: =IF(OR(B7="",G7=""),"",ROUND((G7-B7)*1440,0)) | I7: =IF(H7="","",IF(H7<=Dashboard!$B$6,"Sim","Não")) | J7: Perdido | K7: Fernanda | L7: 30000 | M7: Optou por outra construtora
H8: =IF(OR(B8="",G8=""),"",ROUND((G8-B8)*1440,0)) | I8: =IF(H8="","",IF(H8<=Dashboard!$B$6,"Sim","Não"))
H9: =IF(OR(B9="",G9=""),"",ROUND((G9-B9)*1440,0)) | I9: =IF(H9="","",IF(H9<=Dashboard!$B$6,"Sim","Não"))
H10: =IF(OR(B10="",G10=""),"",ROUND((G10-B10)*1440,0)) | I10: =IF(H10="","",IF(H10<=Dashboard!$B$6,"Sim","Não"))
H11: =IF(OR(B11="",G11=""),"",ROUND((G11-B11)*1440,0)) | I11: =IF(H11="","",IF(H11<=Dashboard!$B$6,"Sim","Não"))
H12: =IF(OR(B12="",G12=""),"",ROUND((G12-B12)*1440,0)) | I12: =IF(H12="","",IF(H12<=Dashboard!$B$6,"Sim","Não"))
H13: =IF(OR(B13="",G13=""),"",ROUND((G13-B13)*1440,0)) | I13: =IF(H13="","",IF(H13<=Dashboard!$B$6,"Sim","Não"))
H14: =IF(OR(B14="",G14=""),"",ROUND((G14-B14)*1440,0)) | I14: =IF(H14="","",IF(H14<=Dashboard!$B$6,"Sim","Não"))
H15: =IF(OR(B15="",G15=""),"",ROUND((G15-B15)*1440,0)) | I15: =IF(H15="","",IF(H15<=Dashboard!$B$6,"Sim","Não"))
H16: =IF(OR(B16="",G16=""),"",ROUND((G16-B16)*1440,0)) | I16: =IF(H16="","",IF(H16<=Dashboard!$B$6,"Sim","Não"))
H17: =IF(OR(B17="",G17=""),"",ROUND((G17-B17)*1440,0)) | I17: =IF(H17="","",IF(H17<=Dashboard!$B$6,"Sim","Não"))
H18: =IF(OR(B18="",G18=""),"",ROUND((G18-B18)*1440,0)) | I18: =IF(H18="","",IF(H18<=Dashboard!$B$6,"Sim","Não"))
H19: =IF(OR(B19="",G19=""),"",ROUND((G19-B19)*1440,0)) | I19: =IF(H19="","",IF(H19<=Dashboard!$B$6,"Sim","Não"))
... H400: =IF(OR(B400="",G400=""),"",ROUND((G400-B400)*1440,0)) | I400: =IF(H400="","",IF(H400<=Dashboard!$B$6,"Sim","Não"))

Sheet Campanhas Google Ads
A1: Campanha | B1: Tipo | C1: Data Início | D1: Orçamento Diário (R$) | E1: Investimento no Período (R$) | F1: Impressões | G1: Cliques | H1: CTR (%) | I1: CPC Médio (R$) | J1: Leads no CRM | K1: Custo por Lead - CPL (R$) | L1: Leads Convertidos em Venda | M1: Taxa de Conversão Lead→Venda (%) | N1: Receita Gerada (R$) | O1: ROI
A2: Reforma Residencial - Pesquisa | B2: Pesquisa | C2: 2026-08-01 | D2: 150 | E2: 4200 | F2: 38000 | G2: 1450 | H2: =IF(F2=0,"",G2/F2) | I2: =IF(G2=0,"",E2/G2) | J2: =COUNTIF('Entrada de Leads'!$C$2:$C$400,A2) | K2: =IF(J2=0,"",E2/J2) | L2: =COUNTIFS('Entrada de Leads'!$C$2:$C$400,A2,'Entrada de Leads'!$J$2:$J$400,"Convertido") | M2: =IF(J2=0,"",L2/J2) | N2: 135000 | O2: =IF(E2=0,"",(N2-E2)/E2)
A3: Construção do Zero - PMax | B3: Performance Max | C3: 2026-08-01 | D3: 300 | E3: 8600 | F3: 61000 | G3: 2100 | H3: =IF(F3=0,"",G3/F3) | I3: =IF(G3=0,"",E3/G3) | J3: =COUNTIF('Entrada de Leads'!$C$2:$C$400,A3) | K3: =IF(J3=0,"",E3/J3) | L3: =COUNTIFS('Entrada de Leads'!$C$2:$C$400,A3,'Entrada de Leads'!$J$2:$J$400,"Convertido") | M3: =IF(J3=0,"",L3/J3) | N3: 410000 | O3: =IF(E3=0,"",(N3-E3)/E3)
A4: Reforma Comercial - Display | B4: Display | C4: 2026-08-10 | D4: 80 | E4: 1900 | F4: 92000 | G4: 980 | H4: =IF(F4=0,"",G4/F4) | I4: =IF(G4=0,"",E4/G4) | J4: =COUNTIF('Entrada de Leads'!$C$2:$C$400,A4) | K4: =IF(J4=0,"",E4/J4) | L4: =COUNTIFS('Entrada de Leads'!$C$2:$C$400,A4,'Entrada de Leads'!$J$2:$J$400,"Convertido") | M4: =IF(J4=0,"",L4/J4) | N4: 0 | O4: =IF(E4=0,"",(N4-E4)/E4)
H5: =IF(F5=0,"",G5/F5) | I5: =IF(G5=0,"",E5/G5) | J5: =IF(A5="","",COUNTIF('Entrada de Leads'!$C$2:$C$400,A5)) | K5: =IF(OR(J5="",J5=0),"",E5/J5) | L5: =IF(A5="","",COUNTIFS('Entrada de Leads'!$C$2:$C$400,A5,'Entrada de Leads'!$J$2:$J$400,"Convertido")) | M5: =IF(OR(J5="",J5=0),"",L5/J5) | O5: =IF(OR(E5="",E5=0),"",(N5-E5)/E5)
H6: =IF(F6=0,"",G6/F6) | I6: =IF(G6=0,"",E6/G6) | J6: =IF(A6="","",COUNTIF('Entrada de Leads'!$C$2:$C$400,A6)) | K6: =IF(OR(J6="",J6=0),"",E6/J6) | L6: =IF(A6="","",COUNTIFS('Entrada de Leads'!$C$2:$C$400,A6,'Entrada de Leads'!$J$2:$J$400,"Convertido")) | M6: =IF(OR(J6="",J6=0),"",L6/J6) | O6: =IF(OR(E6="",E6=0),"",(N6-E6)/E6)
H7: =IF(F7=0,"",G7/F7) | I7: =IF(G7=0,"",E7/G7) | J7: =IF(A7="","",COUNTIF('Entrada de Leads'!$C$2:$C$400,A7)) | K7: =IF(OR(J7="",J7=0),"",E7/J7) | L7: =IF(A7="","",COUNTIFS('Entrada de Leads'!$C$2:$C$400,A7,'Entrada de Leads'!$J$2:$J$400,"Convertido")) | M7: =IF(OR(J7="",J7=0),"",L7/J7) | O7: =IF(OR(E7="",E7=0),"",(N7-E7)/E7)
H8: =IF(F8=0,"",G8/F8) | I8: =IF(G8=0,"",E8/G8) | J8: =IF(A8="","",COUNTIF('Entrada de Leads'!$C$2:$C$400,A8)) | K8: =IF(OR(J8="",J8=0),"",E8/J8) | L8: =IF(A8="","",COUNTIFS('Entrada de Leads'!$C$2:$C$400,A8,'Entrada de Leads'!$J$2:$J$400,"Convertido")) | M8: =IF(OR(J8="",J8=0),"",L8/J8) | O8: =IF(OR(E8="",E8=0),"",(N8-E8)/E8)
H9: =IF(F9=0,"",G9/F9) | I9: =IF(G9=0,"",E9/G9) | J9: =IF(A9="","",COUNTIF('Entrada de Leads'!$C$2:$C$400,A9)) | K9: =IF(OR(J9="",J9=0),"",E9/J9) | L9: =IF(A9="","",COUNTIFS('Entrada de Leads'!$C$2:$C$400,A9,'Entrada de Leads'!$J$2:$J$400,"Convertido")) | M9: =IF(OR(J9="",J9=0),"",L9/J9) | O9: =IF(OR(E9="",E9=0),"",(N9-E9)/E9)
H10: =IF(F10=0,"",G10/F10) | I10: =IF(G10=0,"",E10/G10) | J10: =IF(A10="","",COUNTIF('Entrada de Leads'!$C$2:$C$400,A10)) | K10: =IF(OR(J10="",J10=0),"",E10/J10) | L10: =IF(A10="","",COUNTIFS('Entrada de Leads'!$C$2:$C$400,A10,'Entrada de Leads'!$J$2:$J$400,"Convertido")) | M10: =IF(OR(J10="",J10=0),"",L10/J10) | O10: =IF(OR(E10="",E10=0),"",(N10-E10)/E10)
H11: =IF(F11=0,"",G11/F11) | I11: =IF(G11=0,"",E11/G11) | J11: =IF(A11="","",COUNTIF('Entrada de Leads'!$C$2:$C$400,A11)) | K11: =IF(OR(J11="",J11=0),"",E11/J11) | L11: =IF(A11="","",COUNTIFS('Entrada de Leads'!$C$2:$C$400,A11,'Entrada de Leads'!$J$2:$J$400,"Convertido")) | M11: =IF(OR(J11="",J11=0),"",L11/J11) | O11: =IF(OR(E11="",E11=0),"",(N11-E11)/E11)
H12: =IF(F12=0,"",G12/F12) | I12: =IF(G12=0,"",E12/G12) | J12: =IF(A12="","",COUNTIF('Entrada de Leads'!$C$2:$C$400,A12)) | K12: =IF(OR(J12="",J12=0),"",E12/J12) | L12: =IF(A12="","",COUNTIFS('Entrada de Leads'!$C$2:$C$400,A12,'Entrada de Leads'!$J$2:$J$400,"Convertido")) | M12: =IF(OR(J12="",J12=0),"",L12/J12) | O12: =IF(OR(E12="",E12=0),"",(N12-E12)/E12)
H13: =IF(F13=0,"",G13/F13) | I13: =IF(G13=0,"",E13/G13) | J13: =IF(A13="","",COUNTIF('Entrada de Leads'!$C$2:$C$400,A13)) | K13: =IF(OR(J13="",J13=0),"",E13/J13) | L13: =IF(A13="","",COUNTIFS('Entrada de Leads'!$C$2:$C$400,A13,'Entrada de Leads'!$J$2:$J$400,"Convertido")) | M13: =IF(OR(J13="",J13=0),"",L13/J13) | O13: =IF(OR(E13="",E13=0),"",(N13-E13)/E13)
H14: =IF(F14=0,"",G14/F14) | I14: =IF(G14=0,"",E14/G14) | J14: =IF(A14="","",COUNTIF('Entrada de Leads'!$C$2:$C$400,A14)) | K14: =IF(OR(J14="",J14=0),"",E14/J14) | L14: =IF(A14="","",COUNTIFS('Entrada de Leads'!$C$2:$C$400,A14,'Entrada de Leads'!$J$2:$J$400,"Convertido")) | M14: =IF(OR(J14="",J14=0),"",L14/J14) | O14: =IF(OR(E14="",E14=0),"",(N14-E14)/E14)
H15: =IF(F15=0,"",G15/F15) | I15: =IF(G15=0,"",E15/G15) | J15: =IF(A15="","",COUNTIF('Entrada de Leads'!$C$2:$C$400,A15)) | K15: =IF(OR(J15="",J15=0),"",E15/J15) | L15: =IF(A15="","",COUNTIFS('Entrada de Leads'!$C$2:$C$400,A15,'Entrada de Leads'!$J$2:$J$400,"Convertido")) | M15: =IF(OR(J15="",J15=0),"",L15/J15) | O15: =IF(OR(E15="",E15=0),"",(N15-E15)/E15)
H16: =IF(F16=0,"",G16/F16) | I16: =IF(G16=0,"",E16/G16) | J16: =IF(A16="","",COUNTIF('Entrada de Leads'!$C$2:$C$400,A16)) | K16: =IF(OR(J16="",J16=0),"",E16/J16) | L16: =IF(A16="","",COUNTIFS('Entrada de Leads'!$C$2:$C$400,A16,'Entrada de Leads'!$J$2:$J$400,"Convertido")) | M16: =IF(OR(J16="",J16=0),"",L16/J16) | O16: =IF(OR(E16="",E16=0),"",(N16-E16)/E16)
... H60: =IF(F60=0,"",G60/F60) | I60: =IF(G60=0,"",E60/G60) | J60: =IF(A60="","",COUNTIF('Entrada de Leads'!$C$2:$C$400,A60)) | K60: =IF(OR(J60="",J60=0),"",E60/J60) | L60: =IF(A60="","",COUNTIFS('Entrada de Leads'!$C$2:$C$400,A60,'Entrada de Leads'!$J$2:$J$400,"Convertido")) | M60: =IF(OR(J60="",J60=0),"",L60/J60) | O60: =IF(OR(E60="",E60=0),"",(N60-E60)/E60)

Sheet Leia-me
A1: Controle de Rotina — Entrada Digital (Google Ads)
A2: Como usar esta planilha
B4: O que é | D4: Controle da rotina diária de entrada de leads vindos do Google Ads: acompanhamento do funil, tempo de resposta (SLA) e desempenho das campanhas, no mesmo formato do Controle de Execução de Obra.
B5: Abas | D5: Rotina Diária | Entrada de Leads | Campanhas Google Ads | Dashboard
B6: Células amarelas | D6: São os campos de preenchimento manual (dados do dia a dia, da conta do Google Ads e metas). O resto é calculado por fórmula — não sobrescreva.
B7: Rotina Diária | D7: Checklist diário de tarefas da rotina. Marque Feito/Pendente/N-A em cada tarefa.
B8: Entrada de Leads | D8: Um lead por linha. Preencha data/hora do lead e do 1º contato; o tempo de resposta e o cumprimento do SLA são calculados automaticamente.
B9: Campanhas Google Ads | D9: Um resumo por campanha (dados exportados do Google Ads). O nº de leads no CRM e o custo por lead são calculados a partir da aba Entrada de Leads.
B10: Dashboard | D10: Indicadores do período selecionado (defina as datas em B4/B5) e funil de status.
B11: Meta de SLA | D11: Definida na aba Dashboard, célula B6 (minutos). Usada para calcular o cumprimento de SLA em todas as abas.
