Workbook

Sheet Resumo
A1: CONTROLE DE EXECUÇÃO DE OBRA
A3: Informações da Obra
A4: Nome da Obra: | C4: Residência Família Souza | E4: Cliente: | F4: João Souza
A5: Endereço: | C5: Rua das Flores, 123 - Cidade/UF
A6: Data de Início: | C6: 46027 | E6: Previsão de Término: | F6: 46295
A8: Indicadores Gerais
A9: Valor Total Orçado (Contrato) | C9: =Orçamento!$F$23 -> 212900
A10: Total Executado (Valor Agregado - EV) | C10: =E32 -> 93820
A11: % Avanço Físico da Obra | C11: =IFERROR(C10/C9,0) -> 0.44067637
A12: Total Gasto (Custo Real - AC) | C12: =SUM(Gastos!$G$2:$G$40) -> 69200
A13: Lucro Acumulado (Valor Agregado - Custo Real) | C13: =C10-C12 -> 24620
A14: Margem sobre o Valor Executado (%) | C14: =IFERROR(C13/C10,0) -> 0.2624174
A15: Índice de Desempenho de Custo (IDC = VA / Custo Real) | C15: =IFERROR(C10/C12,0) -> 1.3557803
A16: Saldo do Orçamento a Executar | C16: =C9-C10 -> 119080
A19: Status por Etapa (última medição de cada etapa)
A21: Etapa | B21: Valor Orçado (R$) | C21: Última Medição | D21: % Executado | E21: Valor Agregado (R$) | F21: Gasto Real (R$) | G21: Resultado (R$)
A22: Fundação | B22: =SUMIF(Orçamento!$A$2:$A$22,$A22,Orçamento!$F$2:$F$22) -> 20150 | C22: =IFERROR(IF(_xlfn.MAXIFS(Execução!$A$2:$A$30,Execução!$B$2:$B$30,$A22)=0,"",_xlfn.MAXIFS(Execução!$A$2:$A$30,Execução!$B$2:$B$30,$A22)),"") -> 46042 | D22: =IFERROR(IF($C22="",0,SUMPRODUCT((Execução!$B$2:$B$30=$A22)*(Execução!$A$2:$A$30=$C22)*Execução!$C$2:$C$30)/SUMPRODUCT((Execução!$B$2:$B$30=$A22)*(Execução!$A$2:$A$30=$C22)*1)),0) -> 1 | E22: =$B22*$D22 -> 20150 | F22: =SUMIF(Gastos!$C$2:$C$40,$A22,Gastos!$G$2:$G$40) -> 16000 | G22: =E22-F22 -> 4150
A23: Estrutura | B23: =SUMIF(Orçamento!$A$2:$A$22,$A23,Orçamento!$F$2:$F$22) -> 40000 | C23: =IFERROR(IF(_xlfn.MAXIFS(Execução!$A$2:$A$30,Execução!$B$2:$B$30,$A23)=0,"",_xlfn.MAXIFS(Execução!$A$2:$A$30,Execução!$B$2:$B$30,$A23)),"") -> 46078 | D23: =IFERROR(IF($C23="",0,SUMPRODUCT((Execução!$B$2:$B$30=$A23)*(Execução!$A$2:$A$30=$C23)*Execução!$C$2:$C$30)/SUMPRODUCT((Execução!$B$2:$B$30=$A23)*(Execução!$A$2:$A$30=$C23)*1)),0) -> 1 | E23: =$B23*$D23 -> 40000 | F23: =SUMIF(Gastos!$C$2:$C$40,$A23,Gastos!$G$2:$G$40) -> 20600 | G23: =E23-F23 -> 19400
A24: Alvenaria | B24: =SUMIF(Orçamento!$A$2:$A$22,$A24,Orçamento!$F$2:$F$22) -> 20300 | C24: =IFERROR(IF(_xlfn.MAXIFS(Execução!$A$2:$A$30,Execução!$B$2:$B$30,$A24)=0,"",_xlfn.MAXIFS(Execução!$A$2:$A$30,Execução!$B$2:$B$30,$A24)),"") -> 46099 | D24: =IFERROR(IF($C24="",0,SUMPRODUCT((Execução!$B$2:$B$30=$A24)*(Execução!$A$2:$A$30=$C24)*Execução!$C$2:$C$30)/SUMPRODUCT((Execução!$B$2:$B$30=$A24)*(Execução!$A$2:$A$30=$C24)*1)),0) -> 1 | E24: =$B24*$D24 -> 20300 | F24: =SUMIF(Gastos!$C$2:$C$40,$A24,Gastos!$G$2:$G$40) -> 14300 | G24: =E24-F24 -> 6000
A25: Cobertura | B25: =SUMIF(Orçamento!$A$2:$A$22,$A25,Orçamento!$F$2:$F$22) -> 23400 | C25: =IFERROR(IF(_xlfn.MAXIFS(Execução!$A$2:$A$30,Execução!$B$2:$B$30,$A25)=0,"",_xlfn.MAXIFS(Execução!$A$2:$A$30,Execução!$B$2:$B$30,$A25)),"") -> 46101 | D25: =IFERROR(IF($C25="",0,SUMPRODUCT((Execução!$B$2:$B$30=$A25)*(Execução!$A$2:$A$30=$C25)*Execução!$C$2:$C$30)/SUMPRODUCT((Execução!$B$2:$B$30=$A25)*(Execução!$A$2:$A$30=$C25)*1)),0) -> 0.3 | E25: =$B25*$D25 -> 7020 | F25: =SUMIF(Gastos!$C$2:$C$40,$A25,Gastos!$G$2:$G$40) -> 9800 | G25: =E25-F25 -> -2780
A26: Instalações Elétricas | B26: =SUMIF(Orçamento!$A$2:$A$22,$A26,Orçamento!$F$2:$F$22) -> 27000 | C26: =IFERROR(IF(_xlfn.MAXIFS(Execução!$A$2:$A$30,Execução!$B$2:$B$30,$A26)=0,"",_xlfn.MAXIFS(Execução!$A$2:$A$30,Execução!$B$2:$B$30,$A26)),"") -> 46106 | D26: =IFERROR(IF($C26="",0,SUMPRODUCT((Execução!$B$2:$B$30=$A26)*(Execução!$A$2:$A$30=$C26)*Execução!$C$2:$C$30)/SUMPRODUCT((Execução!$B$2:$B$30=$A26)*(Execução!$A$2:$A$30=$C26)*1)),0) -> 0.15 | E26: =$B26*$D26 -> 4050 | F26: =SUMIF(Gastos!$C$2:$C$40,$A26,Gastos!$G$2:$G$40) -> 3000 | G26: =E26-F26 -> 1050
A27: Instalações Hidráulicas | B27: =SUMIF(Orçamento!$A$2:$A$22,$A27,Orçamento!$F$2:$F$22) -> 23000 | C27: =IFERROR(IF(_xlfn.MAXIFS(Execução!$A$2:$A$30,Execução!$B$2:$B$30,$A27)=0,"",_xlfn.MAXIFS(Execução!$A$2:$A$30,Execução!$B$2:$B$30,$A27)),"") -> 46106 | D27: =IFERROR(IF($C27="",0,SUMPRODUCT((Execução!$B$2:$B$30=$A27)*(Execução!$A$2:$A$30=$C27)*Execução!$C$2:$C$30)/SUMPRODUCT((Execução!$B$2:$B$30=$A27)*(Execução!$A$2:$A$30=$C27)*1)),0) -> 0.1 | E27: =$B27*$D27 -> 2300 | F27: =SUMIF(Gastos!$C$2:$C$40,$A27,Gastos!$G$2:$G$40) -> 2500 | G27: =E27-F27 -> -200
A28: Revestimentos e Acabamento | B28: =SUMIF(Orçamento!$A$2:$A$22,$A28,Orçamento!$F$2:$F$22) -> 37650 | C28: =IFERROR(IF(_xlfn.MAXIFS(Execução!$A$2:$A$30,Execução!$B$2:$B$30,$A28)=0,"",_xlfn.MAXIFS(Execução!$A$2:$A$30,Execução!$B$2:$B$30,$A28)),"") | D28: =IFERROR(IF($C28="",0,SUMPRODUCT((Execução!$B$2:$B$30=$A28)*(Execução!$A$2:$A$30=$C28)*Execução!$C$2:$C$30)/SUMPRODUCT((Execução!$B$2:$B$30=$A28)*(Execução!$A$2:$A$30=$C28)*1)),0) -> 0 | E28: =$B28*$D28 -> 0 | F28: =SUMIF(Gastos!$C$2:$C$40,$A28,Gastos!$G$2:$G$40) -> 0 | G28: =E28-F28 -> 0
A29: Esquadrias | B29: =SUMIF(Orçamento!$A$2:$A$22,$A29,Orçamento!$F$2:$F$22) -> 14400 | C29: =IFERROR(IF(_xlfn.MAXIFS(Execução!$A$2:$A$30,Execução!$B$2:$B$30,$A29)=0,"",_xlfn.MAXIFS(Execução!$A$2:$A$30,Execução!$B$2:$B$30,$A29)),"") | D29: =IFERROR(IF($C29="",0,SUMPRODUCT((Execução!$B$2:$B$30=$A29)*(Execução!$A$2:$A$30=$C29)*Execução!$C$2:$C$30)/SUMPRODUCT((Execução!$B$2:$B$30=$A29)*(Execução!$A$2:$A$30=$C29)*1)),0) -> 0 | E29: =$B29*$D29 -> 0 | F29: =SUMIF(Gastos!$C$2:$C$40,$A29,Gastos!$G$2:$G$40) -> 0 | G29: =E29-F29 -> 0
A30: Limpeza Final e Entrega | B30: =SUMIF(Orçamento!$A$2:$A$22,$A30,Orçamento!$F$2:$F$22) -> 3000 | C30: =IFERROR(IF(_xlfn.MAXIFS(Execução!$A$2:$A$30,Execução!$B$2:$B$30,$A30)=0,"",_xlfn.MAXIFS(Execução!$A$2:$A$30,Execução!$B$2:$B$30,$A30)),"") | D30: =IFERROR(IF($C30="",0,SUMPRODUCT((Execução!$B$2:$B$30=$A30)*(Execução!$A$2:$A$30=$C30)*Execução!$C$2:$C$30)/SUMPRODUCT((Execução!$B$2:$B$30=$A30)*(Execução!$A$2:$A$30=$C30)*1)),0) -> 0 | E30: =$B30*$D30 -> 0 | F30: =SUMIF(Gastos!$C$2:$C$40,$A30,Gastos!$G$2:$G$40) -> 0 | G30: =E30-F30 -> 0
A31: Administrativo/Geral | B31: =SUMIF(Orçamento!$A$2:$A$22,$A31,Orçamento!$F$2:$F$22) -> 4000 | C31: =IFERROR(IF(_xlfn.MAXIFS(Execução!$A$2:$A$30,Execução!$B$2:$B$30,$A31)=0,"",_xlfn.MAXIFS(Execução!$A$2:$A$30,Execução!$B$2:$B$30,$A31)),"") | D31: =IFERROR(IF($C31="",0,SUMPRODUCT((Execução!$B$2:$B$30=$A31)*(Execução!$A$2:$A$30=$C31)*Execução!$C$2:$C$30)/SUMPRODUCT((Execução!$B$2:$B$30=$A31)*(Execução!$A$2:$A$30=$C31)*1)),0) -> 0 | E31: =$B31*$D31 -> 0 | F31: =SUMIF(Gastos!$C$2:$C$40,$A31,Gastos!$G$2:$G$40) -> 3000 | G31: =E31-F31 -> -3000
A32: TOTAL | B32: =SUM(B22:B31) -> 212900 | E32: =SUM(E22:E31) -> 93820 | F32: =SUM(F22:F31) -> 69200 | G32: =E32-F32 -> 24620
A34: Legenda e observações
A35: • Células em amarelo/azul: preencha com seus dados (nas abas Orçamento, Execução, Gastos e nas informações da obra acima). Células em branco/preto contêm fórmulas — não é necessário editá-las. • Valor Agregado (EV): valor do orçamento correspondente ao percentual físico já executado de cada etapa (% Executado × Valor Orçado da Etapa). Reflete o quanto da obra já foi "ganho" financeiramente, independente do que já foi efetivamente gasto ou recebido. • Lucro Acumulado: calculado como Valor Agregado − Custo Real (gasto). Compara o valor da obra já executada com o que já foi gasto para executá-la; se você fatura/recebe valores diferentes do orçado, ajuste essa leitura com base em sua receita real. • IDC (Índice de Desempenho de Custo): acima de 1,00 indica que a obra está custando menos do que o valor executado sugere (bom); abaixo de 1,00 indica estouro de custo.

Sheet Orçamento
A1: Etapa | B1: Item / Serviço | C1: Unidade | D1: Quantidade | E1: Valor Unitário (R$) | F1: Valor Orçado (R$) | G1: % do Orçamento
A2: Fundação | B2: Escavação | C2: m³ | D2: 40 | E2: 80 | F2: =D2*E2 -> 3200 | G2: =IFERROR(F2/$F$23,0) -> 0.015030531
A3: Fundação | B3: Concreto para fundação | C3: m³ | D3: 15 | E3: 650 | F3: =D3*E3 -> 9750 | G3: =IFERROR(F3/$F$23,0) -> 0.045796148
A4: Fundação | B4: Ferragem (aço) | C4: kg | D4: 800 | E4: 9 | F4: =D4*E4 -> 7200 | G4: =IFERROR(F4/$F$23,0) -> 0.033818694
A5: Estrutura | B5: Concreto (pilares e vigas) | C5: m³ | D5: 25 | E5: 700 | F5: =D5*E5 -> 17500 | G5: =IFERROR(F5/$F$23,0) -> 0.082198215
A6: Estrutura | B6: Ferragem da estrutura | C6: kg | D6: 1500 | E6: 9 | F6: =D6*E6 -> 13500 | G6: =IFERROR(F6/$F$23,0) -> 0.063410052
A7: Estrutura | B7: Formas de madeira | C7: m² | D7: 200 | E7: 45 | F7: =D7*E7 -> 9000 | G7: =IFERROR(F7/$F$23,0) -> 0.042273368
A8: Alvenaria | B8: Tijolos/blocos | C8: m² | D8: 300 | E8: 55 | F8: =D8*E8 -> 16500 | G8: =IFERROR(F8/$F$23,0) -> 0.077501174
A9: Alvenaria | B9: Argamassa de assentamento | C9: m³ | D9: 10 | E9: 380 | F9: =D9*E9 -> 3800 | G9: =IFERROR(F9/$F$23,0) -> 0.017848755
A10: Cobertura | B10: Estrutura de telhado (madeirado) | C10: m² | D10: 180 | E10: 90 | F10: =D10*E10 -> 16200 | G10: =IFERROR(F10/$F$23,0) -> 0.076092062
A11: Cobertura | B11: Telhas | C11: m² | D11: 180 | E11: 40 | F11: =D11*E11 -> 7200 | G11: =IFERROR(F11/$F$23,0) -> 0.033818694
A12: Instalações Elétricas | B12: Material elétrico | C12: vb | D12: 1 | E12: 18000 | F12: =D12*E12 -> 18000 | G12: =IFERROR(F12/$F$23,0) -> 0.084546736
A13: Instalações Elétricas | B13: Mão de obra elétrica | C13: vb | D13: 1 | E13: 9000 | F13: =D13*E13 -> 9000 | G13: =IFERROR(F13/$F$23,0) -> 0.042273368
... A22: Administrativo/Geral | B22: Projeto e taxas (ART, alvará) | C22: vb | D22: 1 | E22: 4000 | F22: =D22*E22 -> 4000 | G22: =IFERROR(F22/$F$23,0) -> 0.018788163
A23: TOTAL | F23: =SUM(F2:F22) -> 212900 | G23: =SUM(G2:G22) -> 1

Sheet Execução
A1: Data | B1: Etapa | C1: % Executado Acumulado | D1: Valor Orçado da Etapa (R$) | E1: Valor Agregado (R$) | F1: Observações
A2: 46042 | B2: Fundação | C2: 1 | D2: =IF($B2="","",SUMIF(Orçamento!$A$2:$A$22,$B2,Orçamento!$F$2:$F$22)) -> 20150 | E2: =IF($B2="","",$C2*$D2) -> 20150 | F2: Fundação concluída
A3: 46058 | B3: Estrutura | C3: 0.5 | D3: =IF($B3="","",SUMIF(Orçamento!$A$2:$A$22,$B3,Orçamento!$F$2:$F$22)) -> 40000 | E3: =IF($B3="","",$C3*$D3) -> 20000 | F3: Pilares e vigas do térreo executados
A4: 46078 | B4: Estrutura | C4: 1 | D4: =IF($B4="","",SUMIF(Orçamento!$A$2:$A$22,$B4,Orçamento!$F$2:$F$22)) -> 40000 | E4: =IF($B4="","",$C4*$D4) -> 40000 | F4: Estrutura concluída
A5: 46086 | B5: Alvenaria | C5: 0.6 | D5: =IF($B5="","",SUMIF(Orçamento!$A$2:$A$22,$B5,Orçamento!$F$2:$F$22)) -> 20300 | E5: =IF($B5="","",$C5*$D5) -> 12180
A6: 46099 | B6: Alvenaria | C6: 1 | D6: =IF($B6="","",SUMIF(Orçamento!$A$2:$A$22,$B6,Orçamento!$F$2:$F$22)) -> 20300 | E6: =IF($B6="","",$C6*$D6) -> 20300 | F6: Alvenaria concluída
A7: 46101 | B7: Cobertura | C7: 0.3 | D7: =IF($B7="","",SUMIF(Orçamento!$A$2:$A$22,$B7,Orçamento!$F$2:$F$22)) -> 23400 | E7: =IF($B7="","",$C7*$D7) -> 7020
A8: 46106 | B8: Instalações Elétricas | C8: 0.15 | D8: =IF($B8="","",SUMIF(Orçamento!$A$2:$A$22,$B8,Orçamento!$F$2:$F$22)) -> 27000 | E8: =IF($B8="","",$C8*$D8) -> 4050
A9: 46106 | B9: Instalações Hidráulicas | C9: 0.1 | D9: =IF($B9="","",SUMIF(Orçamento!$A$2:$A$22,$B9,Orçamento!$F$2:$F$22)) -> 23000 | E9: =IF($B9="","",$C9*$D9) -> 2300
D10: =IF($B10="","",SUMIF(Orçamento!$A$2:$A$22,$B10,Orçamento!$F$2:$F$22)) | E10: =IF($B10="","",$C10*$D10)
D11: =IF($B11="","",SUMIF(Orçamento!$A$2:$A$22,$B11,Orçamento!$F$2:$F$22)) | E11: =IF($B11="","",$C11*$D11)
D12: =IF($B12="","",SUMIF(Orçamento!$A$2:$A$22,$B12,Orçamento!$F$2:$F$22)) | E12: =IF($B12="","",$C12*$D12)
D13: =IF($B13="","",SUMIF(Orçamento!$A$2:$A$22,$B13,Orçamento!$F$2:$F$22)) | E13: =IF($B13="","",$C13*$D13)
D14: =IF($B14="","",SUMIF(Orçamento!$A$2:$A$22,$B14,Orçamento!$F$2:$F$22)) | E14: =IF($B14="","",$C14*$D14)
D15: =IF($B15="","",SUMIF(Orçamento!$A$2:$A$22,$B15,Orçamento!$F$2:$F$22)) | E15: =IF($B15="","",$C15*$D15)
D16: =IF($B16="","",SUMIF(Orçamento!$A$2:$A$22,$B16,Orçamento!$F$2:$F$22)) | E16: =IF($B16="","",$C16*$D16)
D17: =IF($B17="","",SUMIF(Orçamento!$A$2:$A$22,$B17,Orçamento!$F$2:$F$22)) | E17: =IF($B17="","",$C17*$D17)
D18: =IF($B18="","",SUMIF(Orçamento!$A$2:$A$22,$B18,Orçamento!$F$2:$F$22)) | E18: =IF($B18="","",$C18*$D18)
D19: =IF($B19="","",SUMIF(Orçamento!$A$2:$A$22,$B19,Orçamento!$F$2:$F$22)) | E19: =IF($B19="","",$C19*$D19)
D20: =IF($B20="","",SUMIF(Orçamento!$A$2:$A$22,$B20,Orçamento!$F$2:$F$22)) | E20: =IF($B20="","",$C20*$D20)
D21: =IF($B21="","",SUMIF(Orçamento!$A$2:$A$22,$B21,Orçamento!$F$2:$F$22)) | E21: =IF($B21="","",$C21*$D21)
... D30: =IF($B30="","",SUMIF(Orçamento!$A$2:$A$22,$B30,Orçamento!$F$2:$F$22)) | E30: =IF($B30="","",$C30*$D30)
A32: Este é um histórico de medições de avanço físico. A cada nova medição de uma etapa, adicione uma nova linha com a data e o novo % acumulado da etapa (não é preciso apagar as medições antigas). A aba Resumo consolida automaticamente sempre a medição mais recente de cada etapa.

Sheet Gastos
A1: Data | B1: Categoria | C1: Etapa | D1: Descrição | E1: Fornecedor | F1: Forma de Pagamento | G1: Valor (R$)
A2: 46027 | B2: Administrativo/Taxas | C2: Administrativo/Geral | D2: ART + alvará de construção | E2: Prefeitura/CREA | F2: Boleto | G2: 1800
A3: 46032 | B3: Material | C3: Fundação | D3: Compra de cimento e areia | E3: Casa do Construtor | F3: PIX | G3: 4200
A4: 46040 | B4: Mão de obra | C4: Fundação | D4: Equipe de fundação | E4: Empreiteira Silva | F4: Transferência (TED/DOC) | G4: 6000
A5: 46047 | B5: Material | C5: Fundação | D5: Ferro e arame recozido | E5: Aço Master | F5: Boleto | G5: 5800
A6: 46055 | B6: Material | C6: Estrutura | D6: Concreto usinado | E6: Concrebras | F6: PIX | G6: 12500
A7: 46061 | B7: Mão de obra | C7: Estrutura | D7: Equipe de armação e forma | E7: Empreiteira Silva | F7: Transferência (TED/DOC) | G7: 7200
A8: 46068 | B8: Outros | C8: Administrativo/Geral | D8: Taxas de projeto complementar | E8: Escritório Eng. Souza | F8: Transferência (TED/DOC) | G8: 1200
A9: 46073 | B9: Equipamento/Aluguel | C9: Estrutura | D9: Aluguel de betoneira | E9: Locadora Obra Fácil | F9: Cartão de Crédito | G9: 900
A10: 46082 | B10: Material | C10: Alvenaria | D10: Blocos e argamassa | E10: Casa do Construtor | F10: PIX | G10: 8900
A11: 46091 | B11: Mão de obra | C11: Alvenaria | D11: Equipe de alvenaria | E11: Empreiteira Costa | F11: Transferência (TED/DOC) | G11: 5400
A12: 46096 | B12: Material | C12: Cobertura | D12: Madeira e telhas | E12: Madeireira Bom Pinho | F12: Boleto | G12: 9800
A13: 46101 | B13: Serviço terceirizado | C13: Instalações Elétricas | D13: Adiantamento eletricista | E13: Eletricista João | F13: PIX | G13: 3000
A14: 46103 | B14: Serviço terceirizado | C14: Instalações Hidráulicas | D14: Adiantamento encanador | E14: Hidráulica Total | F14: PIX | G14: 2500
A41: TOTAL | G41: =SUM(G2:G40) -> 69200

Sheet Listas de Apoio
A1: Etapas da Obra | B1: Categorias de Gasto | C1: Formas de Pagamento
A2: Fundação | B2: Material | C2: Dinheiro
A3: Estrutura | B3: Mão de obra | C3: PIX
A4: Alvenaria | B4: Equipamento/Aluguel | C4: Boleto
A5: Cobertura | B5: Serviço terceirizado | C5: Cartão de Crédito
A6: Instalações Elétricas | B6: Administrativo/Taxas | C6: Transferência (TED/DOC)
A7: Instalações Hidráulicas | B7: Outros | C7: Cheque
A8: Revestimentos e Acabamento
A9: Esquadrias
A10: Limpeza Final e Entrega
A11: Administrativo/Geral
A13: Nota: para adicionar uma nova etapa/categoria/forma de pagamento, inclua uma linha nesta aba e ajuste os intervalos de validação (Dados > Validação de Dados) nas abas Orçamento, Execução e Gastos.
